duplicate_url_discarder_rules/__init__.py
duplicate_url_discarder_rules/py.typed
duplicate_url_discarder_rules/normalizer/main.json
duplicate_url_discarder_rules/queryRemoval/article.json
duplicate_url_discarder_rules/queryRemoval/product.json
duplicate_url_discarder_rules/queryRemoval/utm.json
duplicate_url_discarder_rules/queryRemovalExcept/product.json
duplicate_url_discarder_rules/subpathRemoval/product.json
duplicate_url_discarder_rules-2024.11.5.dist-info/LICENSE
duplicate_url_discarder_rules-2024.11.5.dist-info/METADATA
duplicate_url_discarder_rules-2024.11.5.dist-info/WHEEL
duplicate_url_discarder_rules-2024.11.5.dist-info/top_level.txt
duplicate_url_discarder_rules-2024.11.5.dist-info/RECORD
