Metadata-Version: 2.1
Name: duplicate-url-discarder-rules
Version: 2024.11.5
Summary: The rules for duplicate-url-discarder.
Author-email: Zyte Group Ltd <info@zyte.com>
License: The MIT License (MIT)
Project-URL: Source, https://github.com/zytedata/duplicate-url-discarder-rules
Classifier: Development Status :: 3 - Alpha
Classifier: Intended Audience :: Developers
Classifier: License :: OSI Approved :: MIT License
Classifier: Natural Language :: English
Classifier: Operating System :: OS Independent
Classifier: Programming Language :: Python :: 3
Classifier: Programming Language :: Python :: 3.9
Classifier: Programming Language :: Python :: 3.10
Classifier: Programming Language :: Python :: 3.11
Classifier: Programming Language :: Python :: 3.12
Classifier: Programming Language :: Python :: 3.13
Classifier: Programming Language :: Python :: Implementation :: CPython
Requires-Python: >=3.9
License-File: LICENSE
